crypto_compare-0.0.1.dist-info/DESCRIPTION.rst
crypto_compare-0.0.1.dist-info/RECORD
crypto_compare-0.0.1.dist-info/metadata.json
crypto_compare-0.0.1.dist-info/METADATA
crypto_compare-0.0.1.dist-info/top_level.txt
crypto_compare-0.0.1.dist-info/WHEEL
crypto_compare/client.py
crypto_compare/__init__.py
