Metadata-Version: 2.0
Name: crypto-compare
Version: 0.0.1
Summary: Wrapper for CryptoCompare.com public API
Home-page: https://github.com/BoTreeConsultingTeam/crypto_compare
Author: Parth Barot
Author-email: parth.barot@botreetechnologies.com
License: MIT
Keywords: crypto cryptocurrency wrapper cryptocompare crypto_compare
Platform: UNKNOWN
Classifier: Programming Language :: Python :: 2.7
Requires-Dist: urllib2
